qdk/__init__.py
qdk/base.py
qdk/dagster_types.py
qdk/materialization.py
qdk/mlflow.py
qdk/s3_connection.py
qdk/exporter/__init__.py
qdk/exporter/base.py
qdk/exporter/database.py
qdk/inference/__init__.py
qdk/inference/base.py
qdk/inference/mlflow.py
qdk/loader/__init__.py
qdk/loader/base.py
qdk/loader/dataframe.py
qdk/loader/s3_pickle.py
qdk/loader/sql_query.py
qdk/loader/sql_table.py
qdk/models/__init__.py
qdk/models/word2vec.py
qdk/resources/__init__.py
qdk/resources/io_manager.py
qdk/tests/__init__.py
qdk/tests/test_loaders/__init__.py
qdk/tests/test_loaders/test_DataFrameLoader.py
qdk/tests/test_models/__init__.py
qdk/tests/test_models/test_Word2Vec.py
qdk/tests/test_pipelines/__init__.py
qdk/tests/test_pipelines/test_nlp_pipeline.py
qdk/tests/utils/__init__.py
qdk/tests/utils/dataframe.py
qdk/training/__init__.py
qdk/training/base.py
qdk/training/doc2vec.py
qdk/training/mlflow.py
qdk/training/sklearn.py
qdk/training/word2vec.py
qdk/transform/__init__.py
qdk/transform/base.py
qdk/transform/noun_phrase.py
qdk/transform/tokenize.py
qdk/transform/train_test.py
qdk/transform/yake.py
qdk/utils/__init__.py
qdk/utils/sqlalchemy.py
qdk/utils/text.py
qdk/utils/typing.py
quantile_data_kit-0.0.48.dist-info/METADATA
quantile_data_kit-0.0.48.dist-info/WHEEL
quantile_data_kit-0.0.48.dist-info/top_level.txt
quantile_data_kit-0.0.48.dist-info/RECORD
