Metadata-Version: 2.1
Name: quantile-data-kit
Version: 0.0.48
Summary: An internal Quantile development kit for making working with data easier
Home-page: https://github.com/quantile-development/quantile-data-kit
Author: Jules Huisman
Author-email: jules.huisman@quantile.nl
License: UNKNOWN
Project-URL: Bug Tracker, https://github.com/quantile-development/quantile-data-kit/issues
Platform: UNKNOWN
Classifier: Programming Language :: Python :: 3
Classifier: License :: OSI Approved :: MIT License
Classifier: Operating System :: OS Independent
Requires-Python: >=3.8
Requires-Dist: pandas (==1.3.3)
Requires-Dist: dagster (==1.0.7)
Requires-Dist: dagster-aws (==0.16.7)
Requires-Dist: mlflow (==1.20.2)
Requires-Dist: scikit-learn (==1.0)
Requires-Dist: pyarrow (==6.0.0)
Requires-Dist: markupsafe (==2.0.1)
Requires-Dist: dask (==2021.9.1)
Requires-Dist: dask-ml (==1.9.0)
Requires-Dist: distributed (==2021.9.1)
Requires-Dist: blosc (==1.10.6)
Requires-Dist: lz4 (==3.1.3)
Requires-Dist: s3fs (==2021.10.1)
Requires-Dist: psycopg2-binary (==2.9.2)
Requires-Dist: stop-words (==2018.7.23)
Requires-Dist: yake (==0.4.8)
Requires-Dist: gensim (==4.1.2)
Requires-Dist: spacy (==3.2.0)
Requires-Dist: nltk (==3.6.5)
Provides-Extra: development
Requires-Dist: black (==21.9b0) ; extra == 'development'
Requires-Dist: isort (==5.9.3) ; extra == 'development'
Requires-Dist: setuptools ; extra == 'development'
Requires-Dist: wheel ; extra == 'development'
Requires-Dist: twine ; extra == 'development'
Requires-Dist: ipykernel ; extra == 'development'
Requires-Dist: pytest (==6.2.5) ; extra == 'development'
Provides-Extra: test
Requires-Dist: pytest (==6.2.5) ; extra == 'test'
